apitest/__init__.py
apitest/component.py
apitest/component_test.py
apitest/endpoints.py
apitest/instance.py
apitest/properties.py
apitest/property.py
apitest/test_basic.py
apitest/util.py
evonik_apitest-0.1.2.dist-info/LICENSE
evonik_apitest-0.1.2.dist-info/METADATA
evonik_apitest-0.1.2.dist-info/WHEEL
evonik_apitest-0.1.2.dist-info/top_level.txt
evonik_apitest-0.1.2.dist-info/RECORD
