Metadata-Version: 2.1
Name: evonik-apitest
Version: 0.1.2
Summary: Helpers for testing APIs
Home-page: https://evodl.visualstudio.com/api-test
Author: Benjamin Schiller
Author-email: benjamin.schiller@evonik.com
License: UNKNOWN
Platform: UNKNOWN
Classifier: Programming Language :: Python :: 3
Classifier: License :: OSI Approved :: MIT License
Classifier: Operating System :: OS Independent
Requires-Python: >=3.6
Requires-Dist: exrex
Requires-Dist: uuid
Requires-Dist: pytest
